{
  "generator-jhipster": {
    "applicationType": "monolith",
    "authenticationType": "oauth2",
    "baseName": "Biometrica",
    "blueprints": [],
    "buildTool": "maven",
    "cacheProvider": "infinispan",
    "clientFramework": "react",
    "clientPackageManager": "npm",
    "creationTimestamp": 1703794610286,
    "databaseType": "mongodb",
    "devDatabaseType": "mongodb",
    "devServerPort": 9060,
    "enableHibernateCache": false,
    "enableSwaggerCodegen": "true",
    "enableTranslation": true,
    "entities": ["Fingerprint", "FingerprintTemplate"],
    "gitCompany": "",
    "jhiPrefix": "jhi",
    "jhipsterVersion": "8.1.0",
    "languages": ["fr", "en"],
    "lastLiquibaseTimestamp": 1703794730000,
    "messageBroker": "kafka",
    "nativeLanguage": "fr",
    "packageFolder": "com/zelix/biometrica",
    "packageName": "com.zelix.biometrica",
    "prodDatabaseType": "mongodb",
    "searchEngine": false,
    "serverPort": 8087,
    "serviceDiscoveryType": false,
    "skipUserManagement": true,
    "testFrameworks": [],
    "useSass": true,
    "websocket": "spring-websocket",
    "withAdminUi": true
  },
  "git-company": "drik",
  "git-provider": "GitHub",
  "repository-name": "biometrica-backend"
}
